paoding/__init__.py
paoding/evaluator.py
paoding/pruner.py
paoding/sampler.py
paoding/utility/__init__.py
paoding/utility/adversarial_mnist_fgsm_batch.py
paoding/utility/array_operation.py
paoding/utility/batch_attack.py
paoding/utility/bcolors.py
paoding/utility/dense_layer_surgeon.py
paoding/utility/interval_arithmetic.py
paoding/utility/option.py
paoding/utility/progress_bar.py
paoding/utility/pruning.py
paoding/utility/pruning_criterion.py
paoding/utility/saliency.py
paoding/utility/simulated_propagation.py
paoding/utility/training_from_data.py
paoding/utility/utils.py
paoding/utility/model_profiler/__init__.py
paoding/utility/model_profiler/profiler.py
paoding/utility/model_profiler/utils.py
paoding/utility/surgeon/__init__.py
paoding/utility/surgeon/identify.py
paoding/utility/surgeon/operations.py
paoding/utility/surgeon/surgeon.py
paoding/utility/surgeon/utils.py
paoding/utility/surgeon/utils_dep.py
paoding/utility/surgeon/_utils/__init__.py
paoding/utility/surgeon/_utils/layer.py
paoding/utility/surgeon/_utils/node.py
paoding/utility/surgeon/_utils/tensor_dict.py
tests/__init__.py
tests/test_array_ops.py
tests/test_cnn_pruning.py
tests/test_interval_arith.py
tests/test_pruner.py
tests/test_utils.py
paoding_dl-1.0.0.post3.dist-info/LICENSE
paoding_dl-1.0.0.post3.dist-info/METADATA
paoding_dl-1.0.0.post3.dist-info/WHEEL
paoding_dl-1.0.0.post3.dist-info/top_level.txt
paoding_dl-1.0.0.post3.dist-info/RECORD
