Metadata-Version: 2.1
Name: paoding-dl
Version: 1.0.0.post3
Summary: PAODING-DL: A Data-free Robustness-preserving Neural Network Pruning Toolkit
Home-page: https://github.com/mark-h-meng/nnprune
Author: Mark H. Meng
Author-email: <menghs@i2r.a-star.edu.sg>
Project-URL: Bug Tracker, https://github.com/mark-h-meng/nnprune/issues
Keywords: python,neural network pruning
Classifier: Development Status :: 4 - Beta
Classifier: Intended Audience :: Education
Classifier: Intended Audience :: Science/Research
Classifier: Programming Language :: Python :: 3
Classifier: Operating System :: OS Independent
License-File: LICENSE
Requires-Dist: tensorflow (>=2.3.0)
Requires-Dist: scikit-learn
Requires-Dist: pandas
Requires-Dist: opencv-python (>=4.5numpy)
Requires-Dist: tabulate
Requires-Dist: pydot
